.gitignore
.gitlab-ci.yml
LICENSE
MANIFEST.in
NEWS.rst
OSDneo2
README.rst
requirements.txt
setup.cfg
setup.py
OSD_neo2.egg-info/PKG-INFO
OSD_neo2.egg-info/SOURCES.txt
OSD_neo2.egg-info/dependency_links.txt
OSD_neo2.egg-info/not-zip-safe
OSD_neo2.egg-info/requires.txt
OSD_neo2.egg-info/top_level.txt
osd_neo2/__init__.py
osd_neo2/app.py
osd_neo2/locale.py
osd_neo2/settings.py
osd_neo2/settings_dialog.py
osd_neo2/simple_xkb_wrapper.py
osd_neo2/statusicon.py
osd_neo2/xkb_event_listener.py
osd_neo2/images/ergodox-12.png
osd_neo2/images/ergodox-3.png
osd_neo2/images/ergodox-4.png
osd_neo2/images/ergodox-5.png
osd_neo2/images/ergodox-6.png
osd_neo2/images/ergodox-leer.png
osd_neo2/images/neo-icon.svg
osd_neo2/images/neo2-hauptfeld_ebene1-caps.png
osd_neo2/images/neo2-hauptfeld_ebene1.png
osd_neo2/images/neo2-hauptfeld_ebene2-caps.png
osd_neo2/images/neo2-hauptfeld_ebene2.png
osd_neo2/images/neo2-hauptfeld_ebene3.png
osd_neo2/images/neo2-hauptfeld_ebene4.png
osd_neo2/images/neo2-hauptfeld_ebene5.png
osd_neo2/images/neo2-hauptfeld_ebene6.png
osd_neo2/images/neo2-hauptfeld_leer.png
osd_neo2/images/neo2-ziffernfeld_ebene1-caps.png
osd_neo2/images/neo2-ziffernfeld_ebene1.png
osd_neo2/images/neo2-ziffernfeld_ebene2-caps.png
osd_neo2/images/neo2-ziffernfeld_ebene2.png
osd_neo2/images/neo2-ziffernfeld_ebene3.png
osd_neo2/images/neo2-ziffernfeld_ebene4.png
osd_neo2/images/neo2-ziffernfeld_ebene5.png
osd_neo2/images/neo2-ziffernfeld_ebene6.png
osd_neo2/images/neo2-ziffernfeld_leer.png
osd_neo2/images/update.sh
osd_neo2/po/de/LC_MESSAGES/OSDneo2.mo
osd_neo2/po/de/LC_MESSAGES/OSDneo2.po